twitter_bot_utils/__init__.py
twitter_bot_utils/api.py
twitter_bot_utils/archive.py
twitter_bot_utils/args.py
twitter_bot_utils/cli.py
twitter_bot_utils/confighelper.py
twitter_bot_utils/helpers.py
twitter_bot_utils/tools.py
twitter_bot_utils-0.14.0.dist-info/entry_points.txt
twitter_bot_utils-0.14.0.dist-info/LICENSE
twitter_bot_utils-0.14.0.dist-info/WHEEL
twitter_bot_utils-0.14.0.dist-info/METADATA
twitter_bot_utils-0.14.0.dist-info/RECORD
