Metadata-Version: 2.1
Name: twitter_bot_utils
Version: 0.14.0
Summary: Python utilities for twitter bots
Author-email: Neil Freeman <contact@fakeisthenewreal.org>
Classifier: License :: OSI Approved :: GNU General Public License v3 or later (GPLv3+)
Classifier: Development Status :: 4 - Beta
Classifier: Intended Audience :: Developers
Classifier: Programming Language :: Python :: 3.6
Classifier: Programming Language :: Python :: 3.7
Classifier: Programming Language :: Python :: 3.8
Classifier: Programming Language :: Python :: 3.9
Classifier: Programming Language :: Python :: 3.10
Classifier: Operating System :: OS Independent
Requires-Dist: tweepy >=4.6, <5
Requires-Dist: pyYAML>=4.2
Requires-Dist: sphinx ; extra == "doc"
Requires-Dist: sphinx_rtd_theme ; extra == "doc"
Requires-Dist: pylint ; extra == "pylint"
Requires-Dist: vcrpy==4.1.1 ; extra == "test"
Requires-Dist: mock ; extra == "test"
Project-URL: Home, https://github.com/fitnr/twitter_bot_utils
Provides-Extra: doc
Provides-Extra: pylint
Provides-Extra: test
